d3networkx_psctb/__init__.py
d3networkx_psctb/eventful_dict.py
d3networkx_psctb/eventful_graph.py
d3networkx_psctb/widget.js
d3networkx_psctb/widget.py
psctb/__init__.py
psctb/version.py
psctb/analyse/__init__.py
psctb/analyse/_ratechar.py
psctb/analyse/_thermokin.py
psctb/analyse/_thermokin_file_tools.py
psctb/analyse/_symca/__init__.py
psctb/analyse/_symca/_symca.py
psctb/analyse/_symca/ccobjects.py
psctb/analyse/_symca/symca_toolbox.py
psctb/docs/PyscesToolbox.pdf
psctb/latextools/__init__.py
psctb/latextools/_expressions.py
psctb/modeltools/__init__.py
psctb/modeltools/_paths.py
psctb/modeltools/_pscmanipulate.py
psctb/utils/__init__.py
psctb/utils/config.py
psctb/utils/model_comparing.py
psctb/utils/misc/__init__.py
psctb/utils/misc/_misc.py
psctb/utils/model_graph/__init__.py
psctb/utils/model_graph/_model_graph.py
psctb/utils/plotting/__init__.py
psctb/utils/plotting/_plotting.py
PyscesToolbox-1.1.0.dist-info/LICENCE.txt
PyscesToolbox-1.1.0.dist-info/METADATA
PyscesToolbox-1.1.0.dist-info/WHEEL
PyscesToolbox-1.1.0.dist-info/top_level.txt
PyscesToolbox-1.1.0.dist-info/RECORD
