Metadata-Version: 2.1
Name: PyscesToolbox
Version: 1.1.0
Summary: A set of metabolic model analysis tools for PySCeS.
Home-page: https://github.com/PySCeS/PyscesToolbox
Download-URL: http://github.com/PySCeS/PyscesToolbox/archive/1.1.0.tar.gz
Author: Carl Christensen and Johann Rohwer
Author-email: exe0cdc@gmail.com, j.m.rohwer@gmail.com
License: BSD-3-Clause
Keywords: metabolism,metabolic control analysis,modelling
Classifier: Development Status :: 5 - Production/Stable
Classifier: Intended Audience :: Science/Research
Classifier: Topic :: Scientific/Engineering :: Bio-Informatics
Classifier: License :: OSI Approved :: BSD License
Classifier: Programming Language :: Python :: 3
License-File: LICENCE.txt
Requires-Dist: ipython>=4.0.0
Requires-Dist: numpy
Requires-Dist: sympy
Requires-Dist: pysces
Requires-Dist: matplotlib
Requires-Dist: numpydoc
Requires-Dist: networkx
Requires-Dist: ipywidgets
Requires-Dist: widgetsnbextension
Requires-Dist: jupyter-pip
Requires-Dist: pandas
